easy_tokenizer/__init__.py
easy_tokenizer/__main__.py
easy_tokenizer/normalizer.py
easy_tokenizer/patterns.py
easy_tokenizer/token_with_pos.py
easy_tokenizer/tokenizer.py
easy_tokenizer-0.0.10.dist-info/AUTHORS.rst
easy_tokenizer-0.0.10.dist-info/LICENSE
easy_tokenizer-0.0.10.dist-info/METADATA
easy_tokenizer-0.0.10.dist-info/WHEEL
easy_tokenizer-0.0.10.dist-info/entry_points.txt
easy_tokenizer-0.0.10.dist-info/top_level.txt
easy_tokenizer-0.0.10.dist-info/RECORD
